bmf/BUILTIN_CONFIG.json
bmf/__init__.py
bmf/server/server_gateway.py
bmf/server/__init__.py
bmf/server/server_gateway_new.py
bmf/modules/pass_through.py
bmf/modules/c_module.py
bmf/modules/__init__.py
bmf/modules/frame_sequencer.py
bmf/modules/simple_source.py
bmf/modules/null_sink.py
bmf/cpp_modules/Module_pass_through/libpass_through.so
bmf/cpp_modules/Module_pass_through/meta.info
bmf/cpp_modules/Module_pass_through/libpass_through.so.0.2.0
bmf/cpp_modules/Module_pass_through/libpass_through.so.0
bmf/cpp_modules/Module_GoMockDecoder/libGoMockDecoder.so.0.2.0
bmf/cpp_modules/Module_GoMockDecoder/libGoMockDecoder.so.0
bmf/cpp_modules/Module_GoMockDecoder/meta.info
bmf/cpp_modules/Module_GoMockDecoder/libGoMockDecoder.so
bmf/cpp_modules/Module_clock/libclock.so.0
bmf/cpp_modules/Module_clock/meta.info
bmf/cpp_modules/Module_clock/libclock.so
bmf/cpp_modules/Module_clock/libclock.so.0.2.0
bmf/cpp_modules/Module_MockDecoder/libMockDecoder.so.0.2.0
bmf/cpp_modules/Module_MockDecoder/meta.info
bmf/cpp_modules/Module_MockDecoder/libMockDecoder.so.0
bmf/cpp_modules/Module_MockDecoder/libMockDecoder.so
bmf/cmd/python_wrapper/wrapper.py
bmf/bin/trace_format_log
bmf/bin/test_hmp
bmf/bin/module_manager
bmf/bin/run_bmf_graph
bmf/bin/hmp_perf_main
bmf/lib/libuuid_static.a
bmf/lib/libbmf_module_sdk.so.0
bmf/lib/libbmf_py_loader.so
bmf/lib/libbuiltin_modules.so.0
bmf/lib/libhmp.so
bmf/lib/libbmf_go_loader.so
bmf/lib/libbuiltin_modules.so.0.2.0
bmf/lib/libhmp.so.1.2.0
bmf/lib/libspdlog.a
bmf/lib/libbenchmark_main.a
bmf/lib/libfmt.a
bmf/lib/libbackward.a
bmf/lib/libbuiltin_modules.so
bmf/lib/libengine.so
bmf/lib/libbmf_module_sdk.so
bmf/lib/_hmp.cpython-310-x86_64-linux-gnu.so
bmf/lib/libbmf_module_sdk.so.0.2.0
bmf/lib/libbenchmark.a
bmf/lib/libengine.so.0.2.0
bmf/lib/libengine.so.0
bmf/lib/_bmf.cpython-310-x86_64-linux-gnu.so
bmf/lib/libhmp.so.1
bmf/hmp/__init__.py
bmf/hmp/tracer.py
BabitMF_GPU-0.2.0.dist-info/LICENSE
BabitMF_GPU-0.2.0.dist-info/RECORD
BabitMF_GPU-0.2.0.dist-info/entry_points.txt
BabitMF_GPU-0.2.0.dist-info/WHEEL
BabitMF_GPU-0.2.0.dist-info/METADATA
BabitMF_GPU-0.2.0.dist-info/top_level.txt
